{"digest":"b1f00da854ca81e8fc8879034edfb54f8fb7d6ad","css":".archive-editor {\n  background-color: #3c3836;\n  overflow: auto;\n  contain: strict;\n}\n.archive-editor .archive-container {\n  height: 100%;\n  width: 100%;\n}\n.archive-editor .archive-container .inset-panel {\n  border-width: 0;\n}\n.archive-editor .archive-container .inset-panel .panel-heading {\n  border-radius: 0;\n}\n.archive-editor .archive-container .inset-panel .archive-tree {\n  padding: 5px;\n}\n","imports":[{"path":"static/variables/ui-variables.less","digest":"b28ed6c38c4cfce23f83a1b012a3968aa63fce4c"},{"path":"static/variables/syntax-variables.less","digest":"812c1b7883a023f768773d14294653adcdb932d7"},{"path":"/home/box/.atom/packages/gruvbox-dark-ui/styles/ui-variables.less","digest":"3aa3f78576fea3edc412542a270a8621159e1d57"}],"version":1}